odoo/addons/ssi_revenue_recognition_operating_unit/README.rst
odoo/addons/ssi_revenue_recognition_operating_unit/__init__.py
odoo/addons/ssi_revenue_recognition_operating_unit/__manifest__.py
odoo/addons/ssi_revenue_recognition_operating_unit/models/__init__.py
odoo/addons/ssi_revenue_recognition_operating_unit/models/performance_obligation_acceptance.py
odoo/addons/ssi_revenue_recognition_operating_unit/models/service_contract_performance_obligation.py
odoo/addons/ssi_revenue_recognition_operating_unit/security/ir_rule/performance_obligation_acceptance.xml
odoo/addons/ssi_revenue_recognition_operating_unit/security/ir_rule/service_contract_performance_obligation.xml
odoo/addons/ssi_revenue_recognition_operating_unit/security/res_group/performance_obligation_acceptance.xml
odoo/addons/ssi_revenue_recognition_operating_unit/security/res_group/service_contract_performance_obligation.xml
odoo/addons/ssi_revenue_recognition_operating_unit/static/description/banner.png
odoo/addons/ssi_revenue_recognition_operating_unit/static/description/icon.png
odoo/addons/ssi_revenue_recognition_operating_unit/views/performance_obligation_acceptance_views.xml
odoo/addons/ssi_revenue_recognition_operating_unit/views/service_contract_performance_obligation_views.xml
odoo14_addon_ssi_revenue_recognition_operating_unit-14.0.1.0.0.dist-info/METADATA
odoo14_addon_ssi_revenue_recognition_operating_unit-14.0.1.0.0.dist-info/WHEEL
odoo14_addon_ssi_revenue_recognition_operating_unit-14.0.1.0.0.dist-info/top_level.txt
odoo14_addon_ssi_revenue_recognition_operating_unit-14.0.1.0.0.dist-info/RECORD
