Metadata-Version: 2.1
Name: odoo14-addon-ssi-revenue-recognition-operating-unit
Version: 14.0.1.0.0
Summary: Revenue Recognition + Operating Unit Integration
Home-page: https://simetri-sinergi.id
Author: OpenSynergy Indonesia, PT. Simetri Sinergi Indonesia
License: AGPL-3
Platform: UNKNOWN
Classifier: Programming Language :: Python
Classifier: Framework :: Odoo
Classifier: Framework :: Odoo :: 14.0
Classifier: License :: OSI Approved :: GNU Affero General Public License v3
Requires-Python: >=3.6
Requires-Dist: odoo14-addon-ssi-revenue-recognition
Requires-Dist: odoo14-addon-ssi-service-operating-unit
Requires-Dist: odoo <14.1dev,>=14.0a
